automlmoo/__init__.py
automlmoo/autosklearn_modeling.py
automlmoo/pymoo_optimization.py
automlmoo/solver.py
automlmoo/version.py
automlmoo-0.0.1.2.dist-info/LICENSE.txt
automlmoo-0.0.1.2.dist-info/METADATA
automlmoo-0.0.1.2.dist-info/WHEEL
automlmoo-0.0.1.2.dist-info/top_level.txt
automlmoo-0.0.1.2.dist-info/RECORD
