Metadata-Version: 2.1
Name: automlmoo
Version: 0.0.1.2
Summary: A package for automatic modeling and optimize systems based on data
Home-page: UNKNOWN
Author: Yarens J. Cruz
License: MIT
Platform: UNKNOWN
Requires-Python: >=3.7, <3.10
License-File: LICENSE.txt
Requires-Dist: auto-sklearn ==0.15.0
Requires-Dist: pymoo ==0.6.1.1
Requires-Dist: typeguard ==4.2.1
